cst_modeling/__init__.py
cst_modeling/basic.py
cst_modeling/section.py
cst_modeling/surface.py
cst_modeling/tools/__init__.py
cst_modeling/tools/auxiliary.py
cst_modeling/tools/blwf.py
cst_modeling/tools/naca.py
cst_modeling/tools/xfoil.py
cst_modeling3d-0.2.7.dist-info/LICENSE
cst_modeling3d-0.2.7.dist-info/METADATA
cst_modeling3d-0.2.7.dist-info/WHEEL
cst_modeling3d-0.2.7.dist-info/top_level.txt
cst_modeling3d-0.2.7.dist-info/RECORD
