Metadata-Version: 2.1
Name: cst_modeling3d
Version: 0.2.7
Summary: This is the module of surface/airfoil modeling
Download-URL: https://github.com/swayli94/cst-modeling3d/
Author: Runze LI
Author-email: swayli94@gmail.com
License: MIT
Keywords: CST modeling
Classifier: Programming Language :: Python :: 3
License-File: LICENSE
Requires-Dist: numpy
Requires-Dist: scipy
Requires-Dist: matplotlib
